pymonoprice/__init__.py
pymonoprice/py.typed
pymonoprice-0.5.dist-info/licenses/LICENSE.txt
pymonoprice-0.5.dist-info/METADATA
pymonoprice-0.5.dist-info/WHEEL
pymonoprice-0.5.dist-info/top_level.txt
pymonoprice-0.5.dist-info/zip-safe
pymonoprice-0.5.dist-info/RECORD
