Metadata-Version: 2.4
Name: pymonoprice
Version: 0.5
Summary: Python API for talking to Monoprice 6-zone amplifier
Home-page: https://github.com/etsinko/pymonoprice
Download-URL: https://github.com/etsinko/pymonoprice/archive/0.5.tar.gz
Author: Egor Tsinko
Author-email: etsinko@gmail.com
License: MIT
Classifier: Development Status :: 4 - Beta
Classifier: Programming Language :: Python :: 3
License-File: LICENSE.txt
Requires-Dist: pyserial>=3.4
Requires-Dist: pyserial-asyncio-fast>=0.16
Dynamic: download-url
Dynamic: license-file
